Metadata-Version: 2.1
Name: pfpyspectra
Version: 0.1.0
Summary: Python interface to the C++ Spectra library
Author: pf_test
License: Apache Software License 2.0
Keywords: pfpyspectra
Classifier: Development Status :: 4 - Beta
Classifier: Intended Audience :: Science/Research
Classifier: License :: OSI Approved :: Apache Software License
Classifier: Natural Language :: English
Classifier: Programming Language :: Python :: 3
Classifier: Programming Language :: Python :: 3.6
Classifier: Programming Language :: Python :: 3.7
Classifier: Programming Language :: Python :: 3.8
Provides-Extra: doc
Provides-Extra: test
